{
    "nodes": [
        {
            "id": "carlos-aguilera",
            "group": "Team Member",
            "name": "Carlos Eduardo Aguilera Medina",
            "pfp_src": "/src/assets/images/team/judith-kamalski.jpg"
        },
        {
            "id": "chris-van-der-lans",
            "group": "Team Member",
            "name": "Chris van der Lans",
            "pfp_src": "/src/assets/images/team/judith-kamalski.jpg"
        },
        {
            "id": "shashank-chakravarthy",
            "group": "Team Member",
            "name": "Shashank Chakravarthy",
            "pfp_src": "/src/assets/images/team/judith-kamalski.jpg"
        },
        {
            "id": "sander-van-essel",
            "group": "Team Member",
            "name": "Sander van Essel",
            "pfp_src": "/src/assets/images/team/judith-kamalski.jpg"
        },
        {
            "id": "gijs-van-dijck",
            "group": "Team Member",
            "name": "Gijs van Dijck",
            "pfp_src": "/src/assets/images/team/judith-kamalski.jpg"
        },
        {
            "id": "yenisel-plasencia",
            "group": "Team Member",
            "name": "Yenisel Plasencia",
            "pfp_src": "/src/assets/images/team/judith-kamalski.jpg"
        },
        {
            "id": "bastian-kuppers",
            "group": "Team Member",
            "name": "Bastian Küppers",
            "pfp_src": "/src/assets/images/team/judith-kamalski.jpg"
        },
        {
            "id": "minou-van-der-werf",
            "group": "Team Member",
            "name": "Minou van der Werf",
            "pfp_src": "/src/assets/images/team/judith-kamalski.jpg"
        },
        {
            "id": "lisa-bruggen",
            "group": "Team Member",
            "name": "Lisa Brüggen",
            "pfp_src": "/src/assets/images/team/judith-kamalski.jpg"
        },
        {
            "id": "robert-gianni",
            "group": "Team Member",
            "name": "Robert Gianni",
            "pfp_src": "/src/assets/images/team/judith-kamalski.jpg"
        },
        {
            "id": "stefan-bos",
            "group": "Team Member",
            "name": "Stefan Bos",
            "pfp_src": "/src/assets/images/team/judith-kamalski.jpg"
        },
        {
            "id": "cassy-juhasz",
            "group": "Team Member",
            "name": "Cassy Juhasz",
            "pfp_src": "/src/assets/images/team/judith-kamalski.jpg"
        },
        {
            "id": "max-louwerse",
            "group": "Team Member",
            "name": "Max Louwerse",
            "pfp_src": "/src/assets/images/team/judith-kamalski.jpg"
        },
        {
            "id": "darian-meacham",
            "group": "Team Member",
            "name": "Darian Meacham",
            "pfp_src": "/src/assets/images/team/judith-kamalski.jpg"
        },
        {
            "id": "johan-van-soest",
            "group": "Team Member",
            "name": "Johan van Soest",
            "pfp_src": "/src/assets/images/team/judith-kamalski.jpg"
        },
        {
            "id": "elia-formisano",
            "group": "Team Member",
            "name": "Elia Formisano",
            "pfp_src": "/src/assets/images/team/judith-kamalski.jpg"
        },
        {
            "id": "anna-wilbik",
            "group": "Team Member",
            "name": "Anna Wilbik",
            "pfp_src": "/src/assets/images/team/judith-kamalski.jpg"
        },
        {
            "id": "ali-reza-ghavamipour",
            "group": "Team Member",
            "name": "Ali Reza Ghavamipour",
            "pfp_src": "/src/assets/images/team/judith-kamalski.jpg"
        },
        {
            "id": "rudolf-muller",
            "group": "Team Member",
            "name": "Rudolf Müller",
            "pfp_src": "/src/assets/images/team/judith-kamalski.jpg"
        },
        {
            "id": "andre-dekker",
            "group": "Team Member",
            "name": "André Dekker",
            "pfp_src": "/src/assets/images/team/judith-kamalski.jpg"
        },
        {
            "id": "vivienne-curvers",
            "group": "Team Member",
            "name": "Vivienne Curvers",
            "pfp_src": "/src/assets/images/team/judith-kamalski.jpg"
        },
        {
            "id": "aleksandra-draper",
            "group": "Team Member",
            "name": "Aleksandra Draper",
            "pfp_src": "/src/assets/images/team/judith-kamalski.jpg"
        },
        {
            "id": "judith-kamalski",
            "group": "Team Member",
            "name": "Judith Kamalski",
            "pfp_src": "/src/assets/images/team/judith-kamalski.jpg"
        },
        {
            "id": "lawnotation",
            "group": "Project",
            "name": "Lawnotation"
        },
        {
            "id": "techalliance",
            "group": "Project",
            "name": "Tech Alliance"
        },
        {
            "id": "flying-forward",
            "group": "Project",
            "name": "Flying Forward"
        },
        {
            "id": "elsa",
            "group": "Project",
            "name": "ELSA"
        },
        {
            "id": "audio-to-semantics",
            "group": "Project",
            "name": "Audio to Semantics"
        },
        {
            "id": "plurism-legal-sources",
            "group": "Project",
            "name": "Pluralism of legal sources analyses"
        },
        {
            "id": "faivor",
            "group": "Project",
            "name": "FAIVOR"
        },
        {
            "id": "fair-ai",
            "group": "Project",
            "name": "FAIR4AI"
        },
        {
            "id": "automated-essay-scoring",
            "group": "Project",
            "name": "Automated Essay Scoring"
        },
        {
            "id": "netspar-financial-advice",
            "group": "Project",
            "name": "Netspar Automated Financial Advice"
        },
        {
            "id": "case-law-explorer",
            "group": "Project",
            "name": "Case Law Explorer"
        },
        {
            "id": "better",
            "group": "Project",
            "name": "BETTER"
        },
        {
            "id": "gemeente-sittard-geleen",
            "group": "Project",
            "name": "Gemeente Sittard-Geleen"
        },
        {
            "id": "am-ai-right",
            "group": "Project",
            "name": "Am AI right?"
        },
        {
            "id": "stichting-onderzoek-rechtspleging",
            "group": "Project",
            "name": "Stichting Onderzoek Rechtspleging"
        },
        {
            "id": "strong-aya",
            "group": "Project",
            "name": "Strong-AYA"
        },
        {
            "id": "impact-explorer",
            "group": "Project",
            "name": "Impact Explorer"
        },
        {
            "id": "experiencing-poverty",
            "group": "Project",
            "name": "Experiencing Poverty"
        },
        {
            "id": "priceless",
            "group": "Project",
            "name": "PRICELESS"
        },
        {
            "id": "circular-city",
            "group": "Project",
            "name": "Circular City Challenge"
        },
        {
            "id": "nijsen-project",
            "group": "Project",
            "name": "Nijsen project"
        },
        {
            "id": "factory-shutdown",
            "group": "Project",
            "name": "Factory shutdowns"
        }
    ], 
    "links": [
        {
            "source": "carlos-aguilera",
            "target": "lawnotation"
        },
        {
            "source": "chris-van-der-lans",
            "target": "lawnotation"
        },
        {
            "source": "shashank-chakravarthy",
            "target": "lawnotation"
        },
        {
            "source": "sander-van-essel",
            "target": "lawnotation"
        },
        {
            "source": "gijs-van-dijck",
            "target": "lawnotation"
        },
        {
            "source": "chris-van-der-lans",
            "target": "techalliance"
        },
        {
            "source": "sander-van-essel",
            "target": "techalliance"
        },
        {
            "source": "yenisel-plasencia",
            "target": "techalliance"
        },
        {
            "source": "bastian-kuppers",
            "target": "techalliance"
        },
        {
            "source": "gijs-van-dijck",
            "target": "flying-forward"
        },
        {
            "source": "carlos-aguilera",
            "target": "flying-forward"
        },
        {
            "source": "shashank-chakravarthy",
            "target": "flying-forward"
        },
        {
            "source": "gijs-van-dijck",
            "target": "elsa"
        },
        {
            "source": "minou-van-der-werf",
            "target": "elsa"
        },
        {
            "source": "yenisel-plasencia",
            "target": "elsa"
        },
        {
            "source": "lisa-bruggen",
            "target": "elsa"
        },
        {
            "source": "robert-gianni",
            "target": "elsa"
        },
        {
            "source": "stefan-bos",
            "target": "elsa"
        },
        {
            "source": "cassy-juhasz",
            "target": "elsa"
        },
        {
            "source": "max-louwerse",
            "target": "elsa"
        },
        {
            "source": "darian-meacham",
            "target": "elsa"
        },
        {
            "source": "johan-van-soest",
            "target": "elsa"
        },
        {
            "source": "andre-dekker",
            "target": "elsa"
        },
        {
            "source": "elia-formisano",
            "target": "audio-to-semantics"
        },
        {
            "source": "chris-van-der-lans",
            "target": "audio-to-semantics"
        },
        {
            "source": "rudolf-muller",
            "target": "factory-shutdown"
        },
        {
            "source": "yenisel-plasencia",
            "target": "factory-shutdown"
        }
    ]
}